odoo/addons/stock_inventory_justification/README.rst
odoo/addons/stock_inventory_justification/__init__.py
odoo/addons/stock_inventory_justification/__manifest__.py
odoo/addons/stock_inventory_justification/i18n/fr.po
odoo/addons/stock_inventory_justification/i18n/it.po
odoo/addons/stock_inventory_justification/i18n/stock_inventory_justification.pot
odoo/addons/stock_inventory_justification/i18n/tr.po
odoo/addons/stock_inventory_justification/models/__init__.py
odoo/addons/stock_inventory_justification/models/stock_inventory_justification.py
odoo/addons/stock_inventory_justification/models/stock_move.py
odoo/addons/stock_inventory_justification/models/stock_move_line.py
odoo/addons/stock_inventory_justification/models/stock_quant.py
odoo/addons/stock_inventory_justification/readme/CONTRIBUTORS.rst
odoo/addons/stock_inventory_justification/readme/DESCRIPTION.rst
odoo/addons/stock_inventory_justification/readme/USAGE.rst
odoo/addons/stock_inventory_justification/security/acl_stock_inventory_justification.xml
odoo/addons/stock_inventory_justification/static/description/icon.png
odoo/addons/stock_inventory_justification/static/description/index.html
odoo/addons/stock_inventory_justification/tests/__init__.py
odoo/addons/stock_inventory_justification/tests/test_stock_inventory_justification.py
odoo/addons/stock_inventory_justification/views/stock_inventory_justification.xml
odoo/addons/stock_inventory_justification/views/stock_move_line.xml
odoo/addons/stock_inventory_justification/views/stock_quant.xml
odoo_addon_stock_inventory_justification-16.0.1.0.0.10.dist-info/METADATA
odoo_addon_stock_inventory_justification-16.0.1.0.0.10.dist-info/WHEEL
odoo_addon_stock_inventory_justification-16.0.1.0.0.10.dist-info/top_level.txt
odoo_addon_stock_inventory_justification-16.0.1.0.0.10.dist-info/RECORD
